videopk/__init__.py
videopk/constants.py
videopk/ffmpeg.py
videopk/interfaces.py
videopk/types.py
videopk/video_transcode.py
videopk-2.0.0.dist-info/METADATA
videopk-2.0.0.dist-info/WHEEL
videopk-2.0.0.dist-info/entry_points.txt
videopk-2.0.0.dist-info/licenses/LICENSE
videopk-2.0.0.dist-info/RECORD
