Metadata-Version: 2.3
Name: videopk
Version: 2.0.0
Project-URL: homepage, https://github.com/sebastiengemme/videopk
Author-email: Sébastien Gemme <sgemme7@gmail.com>
Maintainer-email: Sébastien Gemme <sgemme7@gmail.com>
License: Copyright 2024 Sébastien Gemme
License-File: LICENSE
Keywords: transcoding,video
Classifier: Development Status :: 4 - Beta
Classifier: Environment :: Console
Classifier: Environment :: GPU :: NVIDIA CUDA
Classifier: License :: OSI Approved :: MIT License
Classifier: Programming Language :: Python
Classifier: Programming Language :: Python :: 3
Classifier: Topic :: Multimedia :: Video
Classifier: Topic :: Multimedia :: Video :: Conversion
Requires-Python: >=3.8
Requires-Dist: python-ffmpeg
Provides-Extra: dev
Requires-Dist: bumpversion; extra == 'dev'
Requires-Dist: pytest; extra == 'dev'
